backend_sammy_gorilla/__init__.py
backend_sammy_gorilla/__main__.py
backend_sammy_gorilla/config/__init__.py
backend_sammy_gorilla/config/cloudinary_config.py
backend_sammy_gorilla/config/postgre_config.py
backend_sammy_gorilla/routes/gallery.py
backend_sammy_gorilla/routes/health.py
backend_sammy_gorilla-0.1.0.dist-info/METADATA
backend_sammy_gorilla-0.1.0.dist-info/WHEEL
backend_sammy_gorilla-0.1.0.dist-info/RECORD
